snapflow/__init__.py
snapflow/api.py
snapflow/cli/__init__.py
snapflow/cli/app.py
snapflow/cli/commands/__init__.py
snapflow/cli/commands/base.py
snapflow/cli/commands/generate.py
snapflow/cli/commands/output.py
snapflow/cli/commands/run.py
snapflow/core/__init__.py
snapflow/core/component.py
snapflow/core/data_block.py
snapflow/core/declarative/__init__.py
snapflow/core/declarative/base.py
snapflow/core/declarative/dataspace.py
snapflow/core/declarative/execution.py
snapflow/core/declarative/flow.py
snapflow/core/declarative/function.py
snapflow/core/declarative/graph.py
snapflow/core/declarative/interface.py
snapflow/core/environment.py
snapflow/core/execution/__init__.py
snapflow/core/execution/context.py
snapflow/core/execution/execution.py
snapflow/core/execution/run.py
snapflow/core/extraction/__init__.py
snapflow/core/extraction/connection.py
snapflow/core/flattener.py
snapflow/core/function.py
snapflow/core/function_interface.py
snapflow/core/function_interface_manager.py
snapflow/core/function_package.py
snapflow/core/module.py
snapflow/core/operators.py
snapflow/core/persistence/__init__.py
snapflow/core/persistence/api.py
snapflow/core/persistence/base.py
snapflow/core/persistence/data_block.py
snapflow/core/persistence/pydantic.py
snapflow/core/persistence/schema.py
snapflow/core/persistence/state.py
snapflow/core/runtime.py
snapflow/core/sql/__init__.py
snapflow/core/sql/parser.py
snapflow/core/sql/sql_function.py
snapflow/core/storage.py
snapflow/core/typing/__init__.py
snapflow/core/typing/casting.py
snapflow/core/typing/inference.py
snapflow/helpers/__init__.py
snapflow/helpers/connectors/README.md
snapflow/helpers/connectors/__init__.py
snapflow/helpers/connectors/connection.py
snapflow/helpers/connectors/mock_data_source.py
snapflow/logging/__init__.py
snapflow/migrations/README
snapflow/migrations/alembic.ini
snapflow/migrations/env.py
snapflow/migrations/script.py.mako
snapflow/migrations/versions/5e787d339651_initial_migration.py
snapflow-0.7.1.dist-info/entry_points.txt
snapflow-0.7.1.dist-info/LICENSE
snapflow-0.7.1.dist-info/WHEEL
snapflow-0.7.1.dist-info/METADATA
snapflow-0.7.1.dist-info/RECORD
